{
  "resourceType" : "ValueSet",
  "id" : "558aa5a0-bca1-44a8-9b87-f4d7b16b22df-111",
  "url" : "http://hl7.org/fhir/comparison/ValueSet/558aa5a0-bca1-44a8-9b87-f4d7b16b22df-111",
  "name" : "IntersectionUSCoreConditionCategoryCodesAndConditionCategoryCodes",
  "title" : "Intersection of US Core Condition Category Codes And Condition Category Codes",
  "status" : "active",
  "date" : "2021-06-28T16:40:00+00:00",
  "expansion" : {
    "contains" : [{
      "system" : "http://terminology.hl7.org/CodeSystem/condition-category",
      "code" : "problem-list-item",
      "display" : "Problem List Item"
    },
    {
      "system" : "http://terminology.hl7.org/CodeSystem/condition-category",
      "code" : "encounter-diagnosis",
      "display" : "Encounter Diagnosis"
    }]
  }
}